AUTHORS.rst
CHANGES.rst
CONTRIBUTING.rst
LICENSE
MANIFEST.in
README.rst
setup.cfg
setup.py
tox.ini
src/drf_querystringfilter/__init__.py
src/drf_querystringfilter/backend.py
src/drf_querystringfilter/exceptions.py
src/drf_querystringfilter/filters.py
src/drf_querystringfilter.egg-info/PKG-INFO
src/drf_querystringfilter.egg-info/SOURCES.txt
src/drf_querystringfilter.egg-info/dependency_links.txt
src/drf_querystringfilter.egg-info/not-zip-safe
src/drf_querystringfilter.egg-info/requires.txt
src/drf_querystringfilter.egg-info/top_level.txt
src/requirements/install.pip
src/requirements/testing.pip