Metadata-Version: 2.1
Name: drf-querystringfilter
Version: 0.6.0
Summary: Filter backend for DjangoRestFramework able to parse url parameters
Home-page: https://github.com/saxix/drf-querystringfilter
Author: Stefano Apostolico
Author-email: s.apostolico@gmail.com
License: BSD
Keywords: drf-querystringfilter
Platform: UNKNOWN
Classifier: Development Status :: 3 - Alpha
Classifier: Framework :: Django
Classifier: Intended Audience :: Developers
Classifier: License :: OSI Approved :: BSD License
Classifier: Natural Language :: English
Classifier: Programming Language :: Python :: 2
Classifier: Programming Language :: Python :: 2.7
Classifier: Programming Language :: Python :: 3
Classifier: Programming Language :: Python :: 3.5
Provides-Extra: dev
Provides-Extra: test
